paseofyou/__init__.py
paseofyou/movie.py
paseofyou-0.0.15.dist-info/LICENSE
paseofyou-0.0.15.dist-info/METADATA
paseofyou-0.0.15.dist-info/WHEEL
paseofyou-0.0.15.dist-info/top_level.txt
paseofyou-0.0.15.dist-info/RECORD
