Metadata-Version: 2.1
Name: paseofyou
Version: 0.0.15
Summary: A small spider
Home-page: https://github.com/paseofyou/myspider
Author: markstar
Author-email: 863630017@qq.com
License: UNKNOWN
Project-URL: Bug Tracker, https://github.com/paseofyou/myspider/issues
Platform: UNKNOWN
Classifier: Programming Language :: Python :: 3
Classifier: License :: OSI Approved :: MIT License
Classifier: Operating System :: OS Independent
Requires-Python: >=3.6
License-File: LICENSE
Requires-Dist: lxml
Requires-Dist: requests
